pygridsynth/__init__.py
pygridsynth/__main__.py
pygridsynth/cli.py
pygridsynth/config.py
pygridsynth/diophantine.py
pygridsynth/domega_unitary.py
pygridsynth/grid_op.py
pygridsynth/gridsynth.py
pygridsynth/loop_controller.py
pygridsynth/mixed_synthesis.py
pygridsynth/mixed_synthesis_parallel.py
pygridsynth/mixed_synthesis_sequential.py
pygridsynth/mixed_synthesis_utils.py
pygridsynth/multi_qubit_unitary_approximation.py
pygridsynth/mymath.py
pygridsynth/myplot.py
pygridsynth/normal_form.py
pygridsynth/odgp.py
pygridsynth/quantum_circuit.py
pygridsynth/quantum_gate.py
pygridsynth/region.py
pygridsynth/ring.py
pygridsynth/synthesis_of_cliffordT.py
pygridsynth/tdgp.py
pygridsynth/to_upright.py
pygridsynth/two_qubit_unitary_approximation.py
pygridsynth/unitary_approximation.py
pygridsynth-2.0.0.dist-info/licenses/LICENSE
pygridsynth-2.0.0.dist-info/METADATA
pygridsynth-2.0.0.dist-info/WHEEL
pygridsynth-2.0.0.dist-info/entry_points.txt
pygridsynth-2.0.0.dist-info/top_level.txt
pygridsynth-2.0.0.dist-info/RECORD
