Metadata-Version: 2.4
Name: pygridsynth
Version: 2.0.0
Summary: Python version gridsynth program computes approximations of Z-rotations over the Clifford+T gate set
Author-email: Shuntaro Yamamoto <shun0923@g.ecc.u-tokyo.ac.jp>, Nobuyuki Yoshioka <nyoshioka@g.ecc.u-tokyo.ac.jp>
License: MIT License
Project-URL: Homepage, https://github.com/quantum-programming/pygridsynth
Project-URL: Bug Tracker, https://github.com/quantum-programming/pygridsynth/issues
Classifier: Development Status :: 4 - Beta
Classifier: Programming Language :: Python :: 3
Classifier: License :: OSI Approved :: MIT License
Requires-Python: >=3.10
License-File: LICENSE
Requires-Dist: mpmath>=1.3
Requires-Dist: setuptools
Requires-Dist: matplotlib
Requires-Dist: numpy
Requires-Dist: scipy
Requires-Dist: cvxpy
Requires-Dist: numba
Provides-Extra: dev
Requires-Dist: pytest; extra == "dev"
Requires-Dist: flake8; extra == "dev"
Requires-Dist: mypy; extra == "dev"
Requires-Dist: black; extra == "dev"
Requires-Dist: isort; extra == "dev"
Dynamic: license-file
